{
  "_fv": 8,
  "_type": "tool",
  "definition": {
    "renderType": 0,
    "texture": "holystone_pickaxe",
    "customModelName": "Normal",
    "name": "Holystone Pickaxe",
    "specialInfo": [],
    "creativeTab": {
      "value": "CUSTOM:AetherTab"
    },
    "toolType": "Pickaxe",
    "harvestLevel": 1,
    "efficiency": 4.0,
    "attackSpeed": 1.0,
    "enchantability": 14,
    "damageVsEntity": 2.0,
    "usageCount": 131,
    "blocksAffected": [],
    "hasGlow": false,
    "repairItems": [],
    "onBlockDestroyedWithTool": {
      "name": "HolyPickaxeBlockDestroyedWithTool"
    }
  }
}